[
  {
    "Id_Contract": 1032,
    "Contract_Name": "contract #17546",
    "Offer_Id": "17546",
    "Owner": "BRYANT ARLIE L",
    "Group": null,
    "Source": null,
    "Offer_Status": null,
    "Contract_Desc": null,
    "Contract_Date": "/Date(1598385270143)/",
    "effective_date": null,
    "status_desc": "Negotiating (Default)",
    "priority_desc": "High",
    "status": null,
    "TotalCount": 0,
    "nma25": 0.0,
    "nma25ic": null,
    "grosscommssiontot": 0.0,
    "closing_date": null,
    "grantee": null,
    "offer_percent": 1.0
  },
  {
    "Id_Contract": 1031,
    "Contract_Name": "contract #25929",
    "Offer_Id": "25929",
    "Owner": "Bradshaw, Candis",
    "Group": null,
    "Source": null,
    "Offer_Status": null,
    "Contract_Desc": null,
    "Contract_Date": "/Date(1598384865780)/",
    "effective_date": null,
    "status_desc": "Negotiating (Default)",
    "priority_desc": "High",
    "status": null,
    "TotalCount": 0,
    "nma25": 0.0,
    "nma25ic": null,
    "grosscommssiontot": 0.0,
    "closing_date": null,
    "grantee": null,
    "offer_percent": 1.0
  },
  {
    "Id_Contract": 1030,
    "Contract_Name": "Contract #16625",
    "Offer_Id": "16625",
    "Owner": "TOMPKINS JOHN ERWIN",
    "Group": null,
    "Source": null,
    "Offer_Status": null,
    "Contract_Desc": null,
    "Contract_Date": "/Date(1598384795553)/",
    "effective_date": null,
    "status_desc": "Negotiating (Default)",
    "priority_desc": "High",
    "status": null,
    "TotalCount": 0,
    "nma25": 0.0,
    "nma25ic": null,
    "grosscommssiontot": 0.0,
    "closing_date": null,
    "grantee": null,
    "offer_percent": 1.0
  },
  {
    "Id_Contract": 119,
    "Contract_Name": "Ardis, Rudolph C",
    "Offer_Id": "207034",
    "Owner": "RUDOLPH C ARDIS",
    "Group": null,
    "Source": null,
    "Offer_Status": null,
    "Contract_Desc": null,
    "Contract_Date": "/Date(1595826095470)/",
    "effective_date": "/Date(1535740200000)/",
    "status_desc": "Closed",
    "priority_desc": "High",
    "status": null,
    "TotalCount": 0,
    "nma25": 10.72,
    "nma25ic": 10.720002144,
    "grosscommssiontot": 230000.0,
    "closing_date": "/Date(1540319400000)/",
    "grantee": "OMJV1 Minerals Sub LP(100.00000)",
    "offer_percent": 1.0
  },
  {
    "Id_Contract": 118,
    "Contract_Name": "Ardis, Howard R",
    "Offer_Id": "204248",
    "Owner": "HOWARD RALPH ARDIS",
    "Group": null,
    "Source": null,
    "Offer_Status": null,
    "Contract_Desc": null,
    "Contract_Date": "/Date(1595825732660)/",
    "effective_date": "/Date(1535740200000)/",
    "status_desc": "Closed",
    "priority_desc": "High",
    "status": null,
    "TotalCount": 0,
    "nma25": 10.72,
    "nma25ic": 10.720002144,
    "grosscommssiontot": 230000.0,
    "closing_date": "/Date(1540492200000)/",
    "grantee": "OMJV1 Minerals Sub LP(100.00000)",
    "offer_percent": 1.0
  },
  {
    "Id_Contract": 117,
    "Contract_Name": "Kraetz, Mary Marie",
    "Offer_Id": "43574",
    "Owner": "KRAETZ MARY MARIE",
    "Group": null,
    "Source": null,
    "Offer_Status": null,
    "Contract_Desc": null,
    "Contract_Date": "/Date(1595825141350)/",
    "effective_date": "/Date(1535740200000)/",
    "status_desc": "Closed",
    "priority_desc": "High",
    "status": null,
    "TotalCount": 0,
    "nma25": 10.72,
    "nma25ic": 10.720002144,
    "grosscommssiontot": 230000.0,
    "closing_date": "/Date(1545849000000)/",
    "grantee": "OMJV1 Minerals Sub LP(100.00000)",
    "offer_percent": 1.0
  },
  {
    "Id_Contract": 116,
    "Contract_Name": "Kraetz, William R",
    "Offer_Id": "208288",
    "Owner": "WILLIAM R KRAETZ",
    "Group": null,
    "Source": null,
    "Offer_Status": null,
    "Contract_Desc": null,
    "Contract_Date": "/Date(1595824158680)/",
    "effective_date": "/Date(1535740200000)/",
    "status_desc": "Closed",
    "priority_desc": "High",
    "status": null,
    "TotalCount": 0,
    "nma25": 10.72,
    "nma25ic": 10.720002144,
    "grosscommssiontot": 230000.0,
    "closing_date": "/Date(1540319400000)/",
    "grantee": "OMJV1 Minerals Sub LP(100.00000)",
    "offer_percent": 1.0
  },
  {
    "Id_Contract": 115,
    "Contract_Name": "Young, Gary",
    "Offer_Id": "204205",
    "Owner": "GARY D YOUNG",
    "Group": null,
    "Source": null,
    "Offer_Status": null,
    "Contract_Desc": null,
    "Contract_Date": "/Date(1595822972623)/",
    "effective_date": "/Date(1535740200000)/",
    "status_desc": "Closed",
    "priority_desc": "High",
    "status": null,
    "TotalCount": 0,
    "nma25": 10.72,
    "nma25ic": 10.720002144,
    "grosscommssiontot": 230000.0,
    "closing_date": "/Date(1540319400000)/",
    "grantee": "OMJV1 Minerals Sub LP(100.00000)",
    "offer_percent": 1.0
  },
  {
    "Id_Contract": 114,
    "Contract_Name": "Mary Andree Tokoly Living Trust",
    "Offer_Id": "217589",
    "Owner": "TOKOLY MARY ANDREE LVG TRUST",
    "Group": null,
    "Source": null,
    "Offer_Status": null,
    "Contract_Desc": null,
    "Contract_Date": "/Date(1595816988990)/",
    "effective_date": "/Date(1538332200000)/",
    "status_desc": "Closed",
    "priority_desc": "High",
    "status": null,
    "TotalCount": 0,
    "nma25": 82.5,
    "nma25ic": 82.5,
    "grosscommssiontot": 1840000.0,
    "closing_date": "/Date(1539541800000)/",
    "grantee": "OMJV1 Minerals Sub LP(100.00000)",
    "offer_percent": 1.0
  },
  {
    "Id_Contract": 113,
    "Contract_Name": "Mary L. Rothschild Oil and Gas Trust",
    "Offer_Id": "356753",
    "Owner": "ROTHSCHILD MARY L OIL \u0026 GAS TR",
    "Group": null,
    "Source": null,
    "Offer_Status": null,
    "Contract_Desc": null,
    "Contract_Date": "/Date(1595495234917)/",
    "effective_date": null,
    "status_desc": "Title Requested",
    "priority_desc": "High",
    "status": null,
    "TotalCount": 0,
    "nma25": 0.0,
    "nma25ic": 40.0,
    "grosscommssiontot": 500000.0,
    "closing_date": null,
    "grantee": "OMJV1 Minerals Sub LP(100.00000)",
    "offer_percent": 1.0
  },
  {
    "Id_Contract": 112,
    "Contract_Name": "Bates Family Investment Co",
    "Offer_Id": "344925",
    "Owner": null,
    "Group": null,
    "Source": null,
    "Offer_Status": null,
    "Contract_Desc": null,
    "Contract_Date": "/Date(1594962891277)/",
    "effective_date": null,
    "status_desc": "Title Requested",
    "priority_desc": "High",
    "status": null,
    "TotalCount": 0,
    "nma25": 0.0,
    "nma25ic": 106.00700436,
    "grosscommssiontot": 640000.0,
    "closing_date": null,
    "grantee": "OMJV1 Minerals Sub LP(100.00000)",
    "offer_percent": 1.0
  },
  {
    "Id_Contract": 111,
    "Contract_Name": "MCM Permian LLC",
    "Offer_Id": "318020",
    "Owner": null,
    "Group": null,
    "Source": null,
    "Offer_Status": null,
    "Contract_Desc": null,
    "Contract_Date": "/Date(1594272553897)/",
    "effective_date": "/Date(1564597800000)/",
    "status_desc": "Closed",
    "priority_desc": "High",
    "status": null,
    "TotalCount": 0,
    "nma25": 87.29642,
    "nma25ic": 87.2964156896,
    "grosscommssiontot": 2482366.1,
    "closing_date": "/Date(1572892200000)/",
    "grantee": "Mineral WH #1 LLC(100.00000)",
    "offer_percent": 1.0
  },
  {
    "Id_Contract": 110,
    "Contract_Name": "Fletcher, Jack L.",
    "Offer_Id": "216188",
    "Owner": "FLETCHER JACK L",
    "Group": null,
    "Source": null,
    "Offer_Status": null,
    "Contract_Desc": null,
    "Contract_Date": "/Date(1594263909077)/",
    "effective_date": "/Date(1580495400000)/",
    "status_desc": "Title Complete",
    "priority_desc": "High",
    "status": null,
    "TotalCount": 0,
    "nma25": 3.05025,
    "nma25ic": 3.05025406,
    "grosscommssiontot": 24757.5,
    "closing_date": "/Date(1587061800000)/",
    "grantee": "OMJV1 Minerals Sub LP(100.00000)",
    "offer_percent": 1.0
  },
  {
    "Id_Contract": 109,
    "Contract_Name": "Rankin, Lillie J",
    "Offer_Id": "344917",
    "Owner": "RANKIN LILLIE JOSEPHINE",
    "Group": null,
    "Source": null,
    "Offer_Status": null,
    "Contract_Desc": null,
    "Contract_Date": "/Date(1594005500720)/",
    "effective_date": null,
    "status_desc": "Title Complete",
    "priority_desc": "High",
    "status": null,
    "TotalCount": 0,
    "nma25": 5.00859,
    "nma25ic": null,
    "grosscommssiontot": 42000.0,
    "closing_date": null,
    "grantee": "OMJV1 Minerals Sub LP(100.00000)",
    "offer_percent": 1.0
  },
  {
    "Id_Contract": 108,
    "Contract_Name": "Taylor, Joe Tom",
    "Offer_Id": "300568",
    "Owner": "JOE TOM TAYLOR SR",
    "Group": null,
    "Source": null,
    "Offer_Status": null,
    "Contract_Desc": null,
    "Contract_Date": "/Date(1592561000433)/",
    "effective_date": "/Date(1569868200000)/",
    "status_desc": "Closed",
    "priority_desc": "High",
    "status": null,
    "TotalCount": 0,
    "nma25": 5.01438,
    "nma25ic": 5.00057544,
    "grosscommssiontot": 150000.0,
    "closing_date": "/Date(1574015400000)/",
    "grantee": "Mineral WH #1 LLC(100.00000)",
    "offer_percent": 1.0
  },
  {
    "Id_Contract": 107,
    "Contract_Name": "Richmond H Thomason and Sara G Thomason Trust",
    "Offer_Id": "318025",
    "Owner": "THOMASON RICHMOND HUNT",
    "Group": null,
    "Source": null,
    "Offer_Status": null,
    "Contract_Desc": null,
    "Contract_Date": "/Date(1592560046397)/",
    "effective_date": "/Date(1572546600000)/",
    "status_desc": "Closed",
    "priority_desc": "High",
    "status": null,
    "TotalCount": 0,
    "nma25": 70.0,
    "nma25ic": 70.0,
    "grosscommssiontot": 1860000.0,
    "closing_date": "/Date(1576434600000)/",
    "grantee": "Mineral WH #1 LLC(100.00000)",
    "offer_percent": 1.0
  },
  {
    "Id_Contract": 106,
    "Contract_Name": "Houston, Virginia - Arete",
    "Offer_Id": "282488",
    "Owner": "HOUSTON VIRGINIA C MAR TR",
    "Group": null,
    "Source": null,
    "Offer_Status": null,
    "Contract_Desc": null,
    "Contract_Date": "/Date(1592555106517)/",
    "effective_date": "/Date(1572546600000)/",
    "status_desc": "Closed",
    "priority_desc": "High",
    "status": null,
    "TotalCount": 0,
    "nma25": 10.00003,
    "nma25ic": 10.000128,
    "grosscommssiontot": 190000.0,
    "closing_date": "/Date(1577039400000)/",
    "grantee": "Mineral WH #1 LLC(100.00000)",
    "offer_percent": 1.0
  },
  {
    "Id_Contract": 105,
    "Contract_Name": "Lawson, Andrew",
    "Offer_Id": "318069",
    "Owner": "LAWSON ANDREW S",
    "Group": null,
    "Source": null,
    "Offer_Status": null,
    "Contract_Desc": null,
    "Contract_Date": "/Date(1592553737877)/",
    "effective_date": "/Date(1575138600000)/",
    "status_desc": "Closed",
    "priority_desc": "High",
    "status": null,
    "TotalCount": 0,
    "nma25": 2.5,
    "nma25ic": 2.5,
    "grosscommssiontot": 50000.0,
    "closing_date": "/Date(1579026600000)/",
    "grantee": "Mineral WH #1 LLC(100.00000)",
    "offer_percent": 1.0
  },
  {
    "Id_Contract": 104,
    "Contract_Name": "Lawson, Travis",
    "Offer_Id": "318070",
    "Owner": null,
    "Group": null,
    "Source": null,
    "Offer_Status": null,
    "Contract_Desc": null,
    "Contract_Date": "/Date(1592552974987)/",
    "effective_date": "/Date(1575138600000)/",
    "status_desc": "Closed",
    "priority_desc": "High",
    "status": null,
    "TotalCount": 0,
    "nma25": 2.5,
    "nma25ic": 2.5,
    "grosscommssiontot": 50000.0,
    "closing_date": "/Date(1579026600000)/",
    "grantee": "Mineral WH #1 LLC(100.00000)",
    "offer_percent": 1.0
  },
  {
    "Id_Contract": 103,
    "Contract_Name": "Gentry, Doyle",
    "Offer_Id": "316992",
    "Owner": "GENTRY DOYLE",
    "Group": null,
    "Source": null,
    "Offer_Status": null,
    "Contract_Desc": null,
    "Contract_Date": "/Date(1592552021380)/",
    "effective_date": "/Date(1575138600000)/",
    "status_desc": "Closed",
    "priority_desc": "High",
    "status": null,
    "TotalCount": 0,
    "nma25": 9.27934,
    "nma25ic": 9.2791548574,
    "grosscommssiontot": 207000.0,
    "closing_date": "/Date(1580236200000)/",
    "grantee": "Mineral WH #1 LLC(100.00000)",
    "offer_percent": 1.0
  },
  {
    "Id_Contract": 102,
    "Contract_Name": "Main Street Energy - SI Properties",
    "Offer_Id": "318049",
    "Owner": "MAIN STREET ENERGY CO LLC",
    "Group": null,
    "Source": null,
    "Offer_Status": null,
    "Contract_Desc": null,
    "Contract_Date": "/Date(1592480637710)/",
    "effective_date": "/Date(1569868200000)/",
    "status_desc": "Closed",
    "priority_desc": "High",
    "status": null,
    "TotalCount": 0,
    "nma25": 42.92151,
    "nma25ic": 42.921858392,
    "grosscommssiontot": 693353.52,
    "closing_date": "/Date(1575484200000)/",
    "grantee": "OM SUB C II(100.00000)",
    "offer_percent": 1.0
  },
  {
    "Id_Contract": 101,
    "Contract_Name": "Maven Royalty Fund, LP",
    "Offer_Id": "308266",
    "Owner": "MAVEN ROYALTY FUND LP",
    "Group": null,
    "Source": null,
    "Offer_Status": null,
    "Contract_Desc": null,
    "Contract_Date": "/Date(1592463364220)/",
    "effective_date": "/Date(1561487400000)/",
    "status_desc": "Closed",
    "priority_desc": "High",
    "status": null,
    "TotalCount": 0,
    "nma25": 19.07579,
    "nma25ic": 19.0757946222,
    "grosscommssiontot": 413477.0,
    "closing_date": "/Date(1561573800000)/",
    "grantee": "OM SUB C II(100.00000)",
    "offer_percent": 1.0
  },
  {
    "Id_Contract": 100,
    "Contract_Name": "Cooley, David - Arete",
    "Offer_Id": "318016",
    "Owner": "COOLEY DAVID",
    "Group": null,
    "Source": null,
    "Offer_Status": null,
    "Contract_Desc": null,
    "Contract_Date": "/Date(1592450847710)/",
    "effective_date": "/Date(1563129000000)/",
    "status_desc": "Closed",
    "priority_desc": "High",
    "status": null,
    "TotalCount": 0,
    "nma25": 0.69653,
    "nma25ic": 0.69653,
    "grosscommssiontot": 16126.51,
    "closing_date": "/Date(1564079400000)/",
    "grantee": "OM SUB C II(100.00000)",
    "offer_percent": 1.0
  },
  {
    "Id_Contract": 99,
    "Contract_Name": "Cazadores - RUG",
    "Offer_Id": "318010",
    "Owner": "CAZADORES ROYALTY PARTNERS",
    "Group": null,
    "Source": null,
    "Offer_Status": null,
    "Contract_Desc": null,
    "Contract_Date": "/Date(1592382747090)/",
    "effective_date": "/Date(1564597800000)/",
    "status_desc": "Closed",
    "priority_desc": "High",
    "status": null,
    "TotalCount": 0,
    "nma25": 141.88313,
    "nma25ic": 140.4960833072,
    "grosscommssiontot": 3709573.0,
    "closing_date": "/Date(1569954600000)/",
    "grantee": "OneMap II LLC(100.00000)",
    "offer_percent": 1.0
  },
  {
    "Id_Contract": 98,
    "Contract_Name": "MSE - James Hill",
    "Offer_Id": "344897",
    "Owner": "MAIN STREET ENERGY CO LLC",
    "Group": null,
    "Source": null,
    "Offer_Status": null,
    "Contract_Desc": null,
    "Contract_Date": "/Date(1592275706350)/",
    "effective_date": "/Date(1575138600000)/",
    "status_desc": "Closed",
    "priority_desc": "High",
    "status": null,
    "TotalCount": 0,
    "nma25": 2.23219,
    "nma25ic": 2.232192,
    "grosscommssiontot": 48264.25,
    "closing_date": "/Date(1580841000000)/",
    "grantee": "OM SUB C II(100.00000)",
    "offer_percent": 1.0
  },
  {
    "Id_Contract": 97,
    "Contract_Name": "Criswell, Charles",
    "Offer_Id": "309261",
    "Owner": "CRISWELL CHARLES E",
    "Group": null,
    "Source": null,
    "Offer_Status": null,
    "Contract_Desc": null,
    "Contract_Date": "/Date(1592274339470)/",
    "effective_date": "/Date(1564597800000)/",
    "status_desc": "Closed",
    "priority_desc": "High",
    "status": null,
    "TotalCount": 0,
    "nma25": 1.40948,
    "nma25ic": 1.6172205829,
    "grosscommssiontot": 37500.0,
    "closing_date": "/Date(1572892200000)/",
    "grantee": "OM SUB C II(100.00000)",
    "offer_percent": 0.5
  },
  {
    "Id_Contract": 96,
    "Contract_Name": "Perry, Mary W - Arete",
    "Offer_Id": "44917",
    "Owner": "PERRY MARY WENDELIN",
    "Group": null,
    "Source": null,
    "Offer_Status": null,
    "Contract_Desc": null,
    "Contract_Date": "/Date(1592217532710)/",
    "effective_date": "/Date(1563129000000)/",
    "status_desc": "Closed",
    "priority_desc": "High",
    "status": null,
    "TotalCount": 0,
    "nma25": 0.75,
    "nma25ic": 0.7500032,
    "grosscommssiontot": 14586.19,
    "closing_date": "/Date(1564079400000)/",
    "grantee": "OM SUB C II(100.00000)",
    "offer_percent": 1.0
  },
  {
    "Id_Contract": 95,
    "Contract_Name": "Wright, Reba Jo Hall - Arete",
    "Offer_Id": "318017",
    "Owner": "WRIGHT REBA JO HALL",
    "Group": null,
    "Source": null,
    "Offer_Status": null,
    "Contract_Desc": null,
    "Contract_Date": "/Date(1592217056360)/",
    "effective_date": "/Date(1561919400000)/",
    "status_desc": "Closed",
    "priority_desc": "High",
    "status": null,
    "TotalCount": 0,
    "nma25": 1.10584,
    "nma25ic": 1.105839924,
    "grosscommssiontot": 31516.44,
    "closing_date": "/Date(1564079400000)/",
    "grantee": "OM SUB C II(100.00000)",
    "offer_percent": 1.0
  },
  {
    "Id_Contract": 94,
    "Contract_Name": "Hill, Lisa - Arete",
    "Offer_Id": "318015",
    "Owner": "HILL LISA G",
    "Group": null,
    "Source": null,
    "Offer_Status": null,
    "Contract_Desc": null,
    "Contract_Date": "/Date(1592216453987)/",
    "effective_date": "/Date(1561919400000)/",
    "status_desc": "Closed",
    "priority_desc": "High",
    "status": null,
    "TotalCount": 0,
    "nma25": 0.83543,
    "nma25ic": 0.8353632,
    "grosscommssiontot": 10626.77,
    "closing_date": "/Date(1564079400000)/",
    "grantee": "OM SUB C II(100.00000)",
    "offer_percent": 1.0
  },
  {
    "Id_Contract": 93,
    "Contract_Name": "Fisher, Gloria - Arete",
    "Offer_Id": "318014",
    "Owner": null,
    "Group": null,
    "Source": null,
    "Offer_Status": null,
    "Contract_Desc": null,
    "Contract_Date": "/Date(1592216033283)/",
    "effective_date": "/Date(1561919400000)/",
    "status_desc": "Closed",
    "priority_desc": "High",
    "status": null,
    "TotalCount": 0,
    "nma25": 0.83536,
    "nma25ic": 0.8353632,
    "grosscommssiontot": 10626.77,
    "closing_date": "/Date(1564079400000)/",
    "grantee": "OM SUB C II(100.00000)",
    "offer_percent": 1.0
  },
  {
    "Id_Contract": 92,
    "Contract_Name": "Groves, Gerald \u0026 Janell - Arete",
    "Offer_Id": "211307",
    "Owner": "GROVES JERRY \u0026 JANELL",
    "Group": null,
    "Source": null,
    "Offer_Status": null,
    "Contract_Desc": null,
    "Contract_Date": "/Date(1592215009903)/",
    "effective_date": "/Date(1563129000000)/",
    "status_desc": "Closed",
    "priority_desc": "High",
    "status": null,
    "TotalCount": 0,
    "nma25": 0.66666,
    "nma25ic": 0.6666624,
    "grosscommssiontot": 12386.95,
    "closing_date": "/Date(1564079400000)/",
    "grantee": "OM SUB C II(100.00000)",
    "offer_percent": 1.0
  },
  {
    "Id_Contract": 91,
    "Contract_Name": "Cazadores - Howard",
    "Offer_Id": "318003",
    "Owner": "CAZADORES ROYALTY PARTNERS",
    "Group": null,
    "Source": null,
    "Offer_Status": null,
    "Contract_Desc": null,
    "Contract_Date": "/Date(1591768494383)/",
    "effective_date": "/Date(1564597800000)/",
    "status_desc": "Closed",
    "priority_desc": "High",
    "status": null,
    "TotalCount": 0,
    "nma25": 56.52958,
    "nma25ic": 55.256964703,
    "grosscommssiontot": 1675676.25,
    "closing_date": "/Date(1569522600000)/",
    "grantee": "OneMap II LLC(100.00000)",
    "offer_percent": 1.0
  },
  {
    "Id_Contract": 90,
    "Contract_Name": "Henry, Charity - Arete",
    "Offer_Id": "212748",
    "Owner": "HENRY CHARITY A",
    "Group": null,
    "Source": null,
    "Offer_Status": null,
    "Contract_Desc": null,
    "Contract_Date": "/Date(1591689230513)/",
    "effective_date": "/Date(1563129000000)/",
    "status_desc": "Closed",
    "priority_desc": "High",
    "status": null,
    "TotalCount": 0,
    "nma25": 0.61215,
    "nma25ic": 0.6121480871,
    "grosscommssiontot": 14935.9,
    "closing_date": "/Date(1564079400000)/",
    "grantee": "OM SUB C II(100.00000)",
    "offer_percent": 1.0
  },
  {
    "Id_Contract": 89,
    "Contract_Name": "Sutphen, Michael - Arete",
    "Offer_Id": "318022",
    "Owner": "SUTPHEN MICHAEL",
    "Group": null,
    "Source": null,
    "Offer_Status": null,
    "Contract_Desc": null,
    "Contract_Date": "/Date(1591687545110)/",
    "effective_date": "/Date(1561919400000)/",
    "status_desc": "Closed",
    "priority_desc": "High",
    "status": null,
    "TotalCount": 0,
    "nma25": 0.02861,
    "nma25ic": 0.028606552,
    "grosscommssiontot": 587.1,
    "closing_date": "/Date(1565548200000)/",
    "grantee": "OM SUB C II(100.00000)",
    "offer_percent": 1.0
  },
  {
    "Id_Contract": 88,
    "Contract_Name": "Sutphen, Chris - Arete",
    "Offer_Id": "318021",
    "Owner": "SUTPHEN CHRIS",
    "Group": null,
    "Source": null,
    "Offer_Status": null,
    "Contract_Desc": null,
    "Contract_Date": "/Date(1591687325280)/",
    "effective_date": "/Date(1561919400000)/",
    "status_desc": "Closed",
    "priority_desc": "High",
    "status": null,
    "TotalCount": 0,
    "nma25": 0.02861,
    "nma25ic": 0.028606552,
    "grosscommssiontot": 587.1,
    "closing_date": "/Date(1565548200000)/",
    "grantee": "OM SUB C II(100.00000)",
    "offer_percent": 1.0
  },
  {
    "Id_Contract": 87,
    "Contract_Name": "Burgess, Minnie - Arete",
    "Offer_Id": "166263",
    "Owner": "BURGESS MINNIE PEARL",
    "Group": null,
    "Source": null,
    "Offer_Status": null,
    "Contract_Desc": null,
    "Contract_Date": "/Date(1591686685633)/",
    "effective_date": "/Date(1561919400000)/",
    "status_desc": "Closed",
    "priority_desc": "High",
    "status": null,
    "TotalCount": 0,
    "nma25": 4.11956,
    "nma25ic": 4.119556272,
    "grosscommssiontot": 83961.95,
    "closing_date": "/Date(1565548200000)/",
    "grantee": "OM SUB C II(100.00000)",
    "offer_percent": 1.0
  },
  {
    "Id_Contract": 86,
    "Contract_Name": "Douglas, Gary - Arete",
    "Offer_Id": "208992",
    "Owner": "DOUGLAS GARY D/WIFE JENNIFER",
    "Group": null,
    "Source": null,
    "Offer_Status": null,
    "Contract_Desc": null,
    "Contract_Date": "/Date(1591686134430)/",
    "effective_date": "/Date(1561919400000)/",
    "status_desc": "Closed",
    "priority_desc": "High",
    "status": null,
    "TotalCount": 0,
    "nma25": 1.03439,
    "nma25ic": 1.0343937,
    "grosscommssiontot": 24028.35,
    "closing_date": "/Date(1565548200000)/",
    "grantee": "OM SUB C II(100.00000)",
    "offer_percent": 1.0
  },
  {
    "Id_Contract": 85,
    "Contract_Name": "Douglas, Larry - Arete",
    "Offer_Id": "148711",
    "Owner": "DOUGLAS LARRY D/WIFE T CAROL DOUGLAS",
    "Group": null,
    "Source": null,
    "Offer_Status": null,
    "Contract_Desc": null,
    "Contract_Date": "/Date(1591685662190)/",
    "effective_date": "/Date(1561919400000)/",
    "status_desc": "Closed",
    "priority_desc": "High",
    "status": null,
    "TotalCount": 0,
    "nma25": 1.03439,
    "nma25ic": 1.0343937,
    "grosscommssiontot": 24028.35,
    "closing_date": "/Date(1565548200000)/",
    "grantee": "OM SUB C II(100.00000)",
    "offer_percent": 1.0
  },
  {
    "Id_Contract": 84,
    "Contract_Name": "Miller, Jane - Arete",
    "Offer_Id": "318041",
    "Owner": "MILLER JANE ELLEN",
    "Group": null,
    "Source": null,
    "Offer_Status": null,
    "Contract_Desc": null,
    "Contract_Date": "/Date(1591241733597)/",
    "effective_date": "/Date(1564597800000)/",
    "status_desc": "Closed",
    "priority_desc": "High",
    "status": null,
    "TotalCount": 0,
    "nma25": 3.0476,
    "nma25ic": 3.0476032,
    "grosscommssiontot": 73527.6,
    "closing_date": "/Date(1568313000000)/",
    "grantee": "OM SUB C II(100.00000)",
    "offer_percent": 1.0
  },
  {
    "Id_Contract": 83,
    "Contract_Name": "Shrefler, Dee Anna - Arete",
    "Offer_Id": "50162",
    "Owner": "SHREFLER DEE ANNA",
    "Group": null,
    "Source": null,
    "Offer_Status": null,
    "Contract_Desc": null,
    "Contract_Date": "/Date(1591240746773)/",
    "effective_date": "/Date(1561919400000)/",
    "status_desc": "Closed",
    "priority_desc": "High",
    "status": null,
    "TotalCount": 0,
    "nma25": 0.89807,
    "nma25ic": 0.8980683955,
    "grosscommssiontot": 11250.37,
    "closing_date": "/Date(1568313000000)/",
    "grantee": "OM SUB C II(100.00000)",
    "offer_percent": 1.0
  },
  {
    "Id_Contract": 82,
    "Contract_Name": "McDonough, Nancy - Arete",
    "Offer_Id": "134348",
    "Owner": "MCDONOUGH NANCY JEANNE",
    "Group": null,
    "Source": null,
    "Offer_Status": null,
    "Contract_Desc": null,
    "Contract_Date": "/Date(1591149812983)/",
    "effective_date": "/Date(1564597800000)/",
    "status_desc": "Closed",
    "priority_desc": "High",
    "status": null,
    "TotalCount": 0,
    "nma25": 0.41664,
    "nma25ic": 0.41664,
    "grosscommssiontot": 7921.1,
    "closing_date": "/Date(1568313000000)/",
    "grantee": "OM SUB C II(100.00000)",
    "offer_percent": 1.0
  },
  {
    "Id_Contract": 81,
    "Contract_Name": "Conn, Marleta a/k/a Sowers, Marleta - Arete",
    "Offer_Id": "318042",
    "Owner": "CONN MARLITA",
    "Group": null,
    "Source": null,
    "Offer_Status": null,
    "Contract_Desc": null,
    "Contract_Date": "/Date(1591149204137)/",
    "effective_date": "/Date(1567276200000)/",
    "status_desc": "Closed",
    "priority_desc": "High",
    "status": null,
    "TotalCount": 0,
    "nma25": 0.27706,
    "nma25ic": 0.277056,
    "grosscommssiontot": 5054.95,
    "closing_date": "/Date(1568313000000)/",
    "grantee": "OM SUB C II(100.00000)",
    "offer_percent": 1.0
  },
  {
    "Id_Contract": 80,
    "Contract_Name": "Davis, Elbert - Arete",
    "Offer_Id": "135960",
    "Owner": "DAVIS ELBERT RAY",
    "Group": null,
    "Source": null,
    "Offer_Status": null,
    "Contract_Desc": null,
    "Contract_Date": "/Date(1591099030173)/",
    "effective_date": "/Date(1564597800000)/",
    "status_desc": "Closed",
    "priority_desc": "High",
    "status": null,
    "TotalCount": 0,
    "nma25": 0.45285,
    "nma25ic": 0.4527909173,
    "grosscommssiontot": 8436.0,
    "closing_date": "/Date(1568313000000)/",
    "grantee": "OM SUB C II(100.00000)",
    "offer_percent": 1.0
  },
  {
    "Id_Contract": 79,
    "Contract_Name": "Crenshaw, Ronald - Arete",
    "Offer_Id": "318038",
    "Owner": "CRENSHAW RONALD FULLER",
    "Group": null,
    "Source": null,
    "Offer_Status": null,
    "Contract_Desc": null,
    "Contract_Date": "/Date(1591071876043)/",
    "effective_date": "/Date(1564597800000)/",
    "status_desc": "Closed",
    "priority_desc": "High",
    "status": null,
    "TotalCount": 0,
    "nma25": 0.58824,
    "nma25ic": 0.5882368,
    "grosscommssiontot": 5568.9,
    "closing_date": "/Date(1568313000000)/",
    "grantee": "OM SUB C II(100.00000)",
    "offer_percent": 1.0
  },
  {
    "Id_Contract": 78,
    "Contract_Name": "Grevatt, Mary Lou - Arete",
    "Offer_Id": "212946",
    "Owner": "GREVATT MARY LOU",
    "Group": null,
    "Source": null,
    "Offer_Status": null,
    "Contract_Desc": null,
    "Contract_Date": "/Date(1590983508580)/",
    "effective_date": "/Date(1575138600000)/",
    "status_desc": "Closed",
    "priority_desc": "High",
    "status": null,
    "TotalCount": 0,
    "nma25": 0.44117,
    "nma25ic": 0.441168,
    "grosscommssiontot": 8500.84,
    "closing_date": "/Date(1577039400000)/",
    "grantee": "OM SUB C II(100.00000)",
    "offer_percent": 1.0
  },
  {
    "Id_Contract": 77,
    "Contract_Name": "Adams, Agnes - Arete",
    "Offer_Id": "136402",
    "Owner": "ADAMS AGNES LUE",
    "Group": null,
    "Source": null,
    "Offer_Status": null,
    "Contract_Desc": null,
    "Contract_Date": "/Date(1590981918580)/",
    "effective_date": "/Date(1575138600000)/",
    "status_desc": "Closed",
    "priority_desc": "High",
    "status": null,
    "TotalCount": 0,
    "nma25": 0.32978,
    "nma25ic": 0.328406088,
    "grosscommssiontot": 7779.82,
    "closing_date": "/Date(1577039400000)/",
    "grantee": "OM SUB C II(100.00000)",
    "offer_percent": 1.0
  },
  {
    "Id_Contract": 76,
    "Contract_Name": "Beebe, Patricia - Arete",
    "Offer_Id": "56418",
    "Owner": "BEEBE PATRICIA ANN YOUNG",
    "Group": null,
    "Source": null,
    "Offer_Status": null,
    "Contract_Desc": null,
    "Contract_Date": "/Date(1590641029457)/",
    "effective_date": "/Date(1575138600000)/",
    "status_desc": "Closed",
    "priority_desc": "High",
    "status": null,
    "TotalCount": 0,
    "nma25": 1.20492,
    "nma25ic": 1.2049159926,
    "grosscommssiontot": 27922.94,
    "closing_date": "/Date(1577039400000)/",
    "grantee": "OM SUB C II(100.00000)",
    "offer_percent": 1.0
  },
  {
    "Id_Contract": 75,
    "Contract_Name": "Quandt, David - Arete",
    "Offer_Id": "212460",
    "Owner": "QUANDT DAVID",
    "Group": null,
    "Source": null,
    "Offer_Status": null,
    "Contract_Desc": null,
    "Contract_Date": "/Date(1590470208777)/",
    "effective_date": "/Date(1583001000000)/",
    "status_desc": "Closed",
    "priority_desc": "High",
    "status": null,
    "TotalCount": 0,
    "nma25": 0.55173,
    "nma25ic": 0.5517302514,
    "grosscommssiontot": 11524.26,
    "closing_date": "/Date(1584297000000)/",
    "grantee": "OM SUB C II(100.00000)",
    "offer_percent": 1.0
  },
  {
    "Id_Contract": 74,
    "Contract_Name": "Hudson, Geniva - Arete",
    "Offer_Id": "344909",
    "Owner": "HUDSON GENIVA A",
    "Group": null,
    "Source": null,
    "Offer_Status": null,
    "Contract_Desc": null,
    "Contract_Date": "/Date(1590379527163)/",
    "effective_date": "/Date(1583001000000)/",
    "status_desc": "Closed",
    "priority_desc": "High",
    "status": null,
    "TotalCount": 0,
    "nma25": 1.66656,
    "nma25ic": 1.66656,
    "grosscommssiontot": 34841.34,
    "closing_date": "/Date(1584297000000)/",
    "grantee": "OM SUB C II(100.00000)",
    "offer_percent": 1.0
  },
  {
    "Id_Contract": 73,
    "Contract_Name": "Colton, Julia - Arete",
    "Offer_Id": "209588",
    "Owner": "COLTON JULIA",
    "Group": null,
    "Source": null,
    "Offer_Status": null,
    "Contract_Desc": null,
    "Contract_Date": "/Date(1590379117070)/",
    "effective_date": "/Date(1583001000000)/",
    "status_desc": "Closed",
    "priority_desc": "High",
    "status": null,
    "TotalCount": 0,
    "nma25": 0.66665,
    "nma25ic": 0.6666496,
    "grosscommssiontot": 13153.2,
    "closing_date": "/Date(1584297000000)/",
    "grantee": "OM SUB C II(100.00000)",
    "offer_percent": 1.0
  },
  {
    "Id_Contract": 72,
    "Contract_Name": "Hawkins, Carol - Arete",
    "Offer_Id": "142364",
    "Owner": "HAWKINS CAROL L",
    "Group": null,
    "Source": null,
    "Offer_Status": null,
    "Contract_Desc": null,
    "Contract_Date": "/Date(1590375023483)/",
    "effective_date": "/Date(1583001000000)/",
    "status_desc": "Closed",
    "priority_desc": "High",
    "status": null,
    "TotalCount": 0,
    "nma25": 0.39169,
    "nma25ic": 0.41068846,
    "grosscommssiontot": 7768.77,
    "closing_date": "/Date(1584297000000)/",
    "grantee": "OM SUB C II(100.00000)",
    "offer_percent": 1.0
  },
  {
    "Id_Contract": 71,
    "Contract_Name": "Champion, Robert \u0026 Gauntt, Carol",
    "Offer_Id": "153885",
    "Owner": "CHAMPION ROBERT R",
    "Group": null,
    "Source": null,
    "Offer_Status": null,
    "Contract_Desc": null,
    "Contract_Date": "/Date(1590371819733)/",
    "effective_date": "/Date(1583001000000)/",
    "status_desc": "Closed",
    "priority_desc": "High",
    "status": null,
    "TotalCount": 0,
    "nma25": 0.31248,
    "nma25ic": 0.31248,
    "grosscommssiontot": 5679.67,
    "closing_date": "/Date(1584297000000)/",
    "grantee": "OM SUB C II(100.00000)",
    "offer_percent": 1.0
  },
  {
    "Id_Contract": 70,
    "Contract_Name": "Stevens, Landon Jared",
    "Offer_Id": "344916",
    "Owner": null,
    "Group": null,
    "Source": null,
    "Offer_Status": null,
    "Contract_Desc": null,
    "Contract_Date": "/Date(1591869129160)/",
    "effective_date": "/Date(1590949800000)/",
    "status_desc": "Closed",
    "priority_desc": "High",
    "status": null,
    "TotalCount": 0,
    "nma25": 18.0,
    "nma25ic": 18.00064,
    "grosscommssiontot": 208000.0,
    "closing_date": "/Date(1592245800000)/",
    "grantee": "OMJV1 Minerals Sub LP(100.00000)",
    "offer_percent": 1.0
  },
  {
    "Id_Contract": 69,
    "Contract_Name": "Connelly, William III",
    "Offer_Id": "344908",
    "Owner": "CONNELLY WILLIAM III",
    "Group": null,
    "Source": null,
    "Offer_Status": null,
    "Contract_Desc": null,
    "Contract_Date": "/Date(1590134584763)/",
    "effective_date": "/Date(1583001000000)/",
    "status_desc": "Closed",
    "priority_desc": "High",
    "status": null,
    "TotalCount": 0,
    "nma25": 0.40936,
    "nma25ic": 0.409362304,
    "grosscommssiontot": 8558.89,
    "closing_date": "/Date(1584297000000)/",
    "grantee": "OM SUB C II(100.00000)",
    "offer_percent": 1.0
  },
  {
    "Id_Contract": 68,
    "Contract_Name": "Moore, William",
    "Offer_Id": "175776",
    "Owner": "MOORE WILLIAM R",
    "Group": null,
    "Source": null,
    "Offer_Status": null,
    "Contract_Desc": null,
    "Contract_Date": "/Date(1590134006240)/",
    "effective_date": "/Date(1583001000000)/",
    "status_desc": "Closed",
    "priority_desc": "High",
    "status": null,
    "TotalCount": 0,
    "nma25": 1.5131,
    "nma25ic": 1.5130999784,
    "grosscommssiontot": 22685.05,
    "closing_date": "/Date(1584297000000)/",
    "grantee": "OM SUB C II(100.00000)",
    "offer_percent": 1.0
  },
  {
    "Id_Contract": 67,
    "Contract_Name": "Carmichael, Mary Margaret",
    "Offer_Id": "175775",
    "Owner": "CARMICHAEL MARY MARGARET",
    "Group": null,
    "Source": null,
    "Offer_Status": null,
    "Contract_Desc": null,
    "Contract_Date": "/Date(1590133273090)/",
    "effective_date": "/Date(1583001000000)/",
    "status_desc": "Closed",
    "priority_desc": "High",
    "status": null,
    "TotalCount": 0,
    "nma25": 0.56095,
    "nma25ic": 0.560953296,
    "grosscommssiontot": 8052.03,
    "closing_date": "/Date(1584297000000)/",
    "grantee": "OM SUB C II(100.00000)",
    "offer_percent": 1.0
  },
  {
    "Id_Contract": 66,
    "Contract_Name": "Taylor, Nancy Hamlin",
    "Offer_Id": "191833",
    "Owner": "TAYLOR NANCY HAMLIN",
    "Group": null,
    "Source": null,
    "Offer_Status": null,
    "Contract_Desc": null,
    "Contract_Date": "/Date(1590118249500)/",
    "effective_date": "/Date(1583001000000)/",
    "status_desc": "Closed",
    "priority_desc": "High",
    "status": null,
    "TotalCount": 0,
    "nma25": 0.8323,
    "nma25ic": 0.8322966,
    "grosscommssiontot": 21521.05,
    "closing_date": "/Date(1584297000000)/",
    "grantee": "OM SUB C II(100.00000)",
    "offer_percent": 1.0
  },
  {
    "Id_Contract": 65,
    "Contract_Name": "Willey, Elmer C",
    "Offer_Id": "344907",
    "Owner": "WILLEY ELMER C",
    "Group": null,
    "Source": null,
    "Offer_Status": null,
    "Contract_Desc": null,
    "Contract_Date": "/Date(1590117347487)/",
    "effective_date": "/Date(1583001000000)/",
    "status_desc": "Closed",
    "priority_desc": "High",
    "status": null,
    "TotalCount": 0,
    "nma25": 0.27706,
    "nma25ic": 0.277056,
    "grosscommssiontot": 5308.0,
    "closing_date": "/Date(1584297000000)/",
    "grantee": "OM SUB C II(100.00000)",
    "offer_percent": 1.0
  },
  {
    "Id_Contract": 64,
    "Contract_Name": "Parnell, John",
    "Offer_Id": "318043",
    "Owner": "PARNELL JOHN E",
    "Group": null,
    "Source": null,
    "Offer_Status": null,
    "Contract_Desc": null,
    "Contract_Date": "/Date(1590058922283)/",
    "effective_date": "/Date(1583001000000)/",
    "status_desc": "Closed",
    "priority_desc": "High",
    "status": null,
    "TotalCount": 0,
    "nma25": 0.75,
    "nma25ic": 0.75,
    "grosscommssiontot": 17660.61,
    "closing_date": "/Date(1584297000000)/",
    "grantee": "OM SUB C II(100.00000)",
    "offer_percent": 1.0
  },
  {
    "Id_Contract": 63,
    "Contract_Name": "Cade, Ginger",
    "Offer_Id": "135945",
    "Owner": "CADE GINGER ANN",
    "Group": null,
    "Source": null,
    "Offer_Status": null,
    "Contract_Desc": null,
    "Contract_Date": "/Date(1590057846923)/",
    "effective_date": "/Date(1583001000000)/",
    "status_desc": "Closed",
    "priority_desc": "High",
    "status": null,
    "TotalCount": 0,
    "nma25": 0.678,
    "nma25ic": 0.6780011904,
    "grosscommssiontot": 6605.34,
    "closing_date": "/Date(1584297000000)/",
    "grantee": "OM SUB C II(100.00000)",
    "offer_percent": 1.0
  },
  {
    "Id_Contract": 62,
    "Contract_Name": "Lawrence, David",
    "Offer_Id": "344913",
    "Owner": "LAWRENCE DAVID B",
    "Group": null,
    "Source": null,
    "Offer_Status": null,
    "Contract_Desc": null,
    "Contract_Date": "/Date(1590055698297)/",
    "effective_date": "/Date(1583001000000)/",
    "status_desc": "Closed",
    "priority_desc": "High",
    "status": null,
    "TotalCount": 0,
    "nma25": 0.24,
    "nma25ic": 0.24,
    "grosscommssiontot": 3154.0,
    "closing_date": "/Date(1584297000000)/",
    "grantee": "OM SUB C II(100.00000)",
    "offer_percent": 1.0
  },
  {
    "Id_Contract": 61,
    "Contract_Name": "Hay, Robert",
    "Offer_Id": "212819",
    "Owner": "HAY ROBERT",
    "Group": null,
    "Source": null,
    "Offer_Status": null,
    "Contract_Desc": null,
    "Contract_Date": "/Date(1590048883003)/",
    "effective_date": "/Date(1583001000000)/",
    "status_desc": "Closed",
    "priority_desc": "High",
    "status": null,
    "TotalCount": 0,
    "nma25": 0.63055,
    "nma25ic": 0.630549992,
    "grosscommssiontot": 12820.44,
    "closing_date": "/Date(1584297000000)/",
    "grantee": "OM SUB C II(100.00000)",
    "offer_percent": 1.0
  },
  {
    "Id_Contract": 60,
    "Contract_Name": "Burton, Jane",
    "Offer_Id": "195241",
    "Owner": "BURTON JANE",
    "Group": null,
    "Source": null,
    "Offer_Status": null,
    "Contract_Desc": null,
    "Contract_Date": "/Date(1589949102847)/",
    "effective_date": "/Date(1585679400000)/",
    "status_desc": "Closed",
    "priority_desc": "High",
    "status": null,
    "TotalCount": 0,
    "nma25": 6.1144,
    "nma25ic": 6.114375488,
    "grosscommssiontot": 115000.0,
    "closing_date": "/Date(1591209000000)/",
    "grantee": "OMJV1 Minerals Sub LP(100.00000)",
    "offer_percent": 1.0
  },
  {
    "Id_Contract": 59,
    "Contract_Name": "Davis, Troy C",
    "Offer_Id": "211754",
    "Owner": "DAVIS TROY C",
    "Group": null,
    "Source": null,
    "Offer_Status": null,
    "Contract_Desc": null,
    "Contract_Date": "/Date(1589862444400)/",
    "effective_date": "/Date(1583001000000)/",
    "status_desc": "Closed",
    "priority_desc": "High",
    "status": null,
    "TotalCount": 0,
    "nma25": 0.50002,
    "nma25ic": 0.5000192,
    "grosscommssiontot": 12583.88,
    "closing_date": "/Date(1584297000000)/",
    "grantee": "OM SUB C II(100.00000)",
    "offer_percent": 1.0
  },
  {
    "Id_Contract": 58,
    "Contract_Name": "Douglas P Balser Revocable Trust",
    "Offer_Id": "134464",
    "Owner": "BALSER DOUGLAS P",
    "Group": null,
    "Source": null,
    "Offer_Status": null,
    "Contract_Desc": null,
    "Contract_Date": "/Date(1589859359827)/",
    "effective_date": "/Date(1583001000000)/",
    "status_desc": "Closed",
    "priority_desc": "High",
    "status": null,
    "TotalCount": 0,
    "nma25": 0.37699,
    "nma25ic": 0.376993796,
    "grosscommssiontot": 8077.88,
    "closing_date": "/Date(1584297000000)/",
    "grantee": "OM SUB C II(100.00000)",
    "offer_percent": 1.0
  },
  {
    "Id_Contract": 57,
    "Contract_Name": "Cox, Shae Lara",
    "Offer_Id": "344890",
    "Owner": null,
    "Group": null,
    "Source": null,
    "Offer_Status": null,
    "Contract_Desc": null,
    "Contract_Date": "/Date(1591154900537)/",
    "effective_date": "/Date(1588271400000)/",
    "status_desc": "Closed",
    "priority_desc": "High",
    "status": null,
    "TotalCount": 0,
    "nma25": 109.54563,
    "nma25ic": 109.545945,
    "grosscommssiontot": 1875194.0,
    "closing_date": "/Date(1591209000000)/",
    "grantee": "OMJV1 Minerals Sub LP(100.00000)",
    "offer_percent": 0.5
  },
  {
    "Id_Contract": 56,
    "Contract_Name": "Blaylock Trust - Monticello Energy Partners",
    "Offer_Id": "232733",
    "Owner": "Blaylock Trust",
    "Group": null,
    "Source": null,
    "Offer_Status": null,
    "Contract_Desc": null,
    "Contract_Date": "/Date(1588332522523)/",
    "effective_date": "/Date(1561919400000)/",
    "status_desc": "Closed",
    "priority_desc": "High",
    "status": null,
    "TotalCount": 0,
    "nma25": 29.56944,
    "nma25ic": 29.5694448,
    "grosscommssiontot": 427875.0,
    "closing_date": "/Date(1564511400000)/",
    "grantee": "OneMap II LLC(100.00000)",
    "offer_percent": 1.0
  },
  {
    "Id_Contract": 55,
    "Contract_Name": "RKT Holdings LLC",
    "Offer_Id": "279077",
    "Owner": "RKT HOLDINGS LLC",
    "Group": null,
    "Source": null,
    "Offer_Status": null,
    "Contract_Desc": null,
    "Contract_Date": "/Date(1590047373583)/",
    "effective_date": "/Date(1559327400000)/",
    "status_desc": "Closed",
    "priority_desc": "High",
    "status": null,
    "TotalCount": 0,
    "nma25": 81.23417,
    "nma25ic": 80.809191424,
    "grosscommssiontot": 2167784.0,
    "closing_date": "/Date(1561314600000)/",
    "grantee": "OMJV1 Minerals Sub LP(50.00000),OneMap II LLC(50.00000)",
    "offer_percent": 1.0
  },
  {
    "Id_Contract": 54,
    "Contract_Name": "Lewis Sec 15 - OMJV1 to OMII",
    "Offer_Id": "318011",
    "Owner": "Lewis Section 15 Divestiture",
    "Group": null,
    "Source": null,
    "Offer_Status": null,
    "Contract_Desc": null,
    "Contract_Date": "/Date(1586169323887)/",
    "effective_date": "/Date(1554057000000)/",
    "status_desc": "Closed",
    "priority_desc": "High",
    "status": null,
    "TotalCount": 0,
    "nma25": 200.19062,
    "nma25ic": 200.19136,
    "grosscommssiontot": 5988976.08,
    "closing_date": "/Date(1562869800000)/",
    "grantee": "OneMap II LLC(100.00000)",
    "offer_percent": 0.5
  },
  {
    "Id_Contract": 53,
    "Contract_Name": "Genevieve H. Mitchell 2019 Nonexempt Trust",
    "Offer_Id": "301817",
    "Owner": "MITCHELL JOSEPH D JR",
    "Group": null,
    "Source": null,
    "Offer_Status": null,
    "Contract_Desc": null,
    "Contract_Date": "/Date(1586157532113)/",
    "effective_date": "/Date(1572546600000)/",
    "status_desc": "Closed",
    "priority_desc": "High",
    "status": null,
    "TotalCount": 0,
    "nma25": 5.25,
    "nma25ic": 5.250048,
    "grosscommssiontot": 143100.0,
    "closing_date": "/Date(1575311400000)/",
    "grantee": "OneMap II LLC(100.00000)",
    "offer_percent": 1.0
  },
  {
    "Id_Contract": 52,
    "Contract_Name": "McKee, Sally Jayne",
    "Offer_Id": "216476",
    "Owner": "MCKEE SALLY JANE",
    "Group": null,
    "Source": null,
    "Offer_Status": null,
    "Contract_Desc": null,
    "Contract_Date": "/Date(1586153697643)/",
    "effective_date": "/Date(1569868200000)/",
    "status_desc": "Closed",
    "priority_desc": "High",
    "status": null,
    "TotalCount": 0,
    "nma25": 5.25039,
    "nma25ic": 5.25039273,
    "grosscommssiontot": 61000.0,
    "closing_date": "/Date(1575311400000)/",
    "grantee": "OneMap II LLC(100.00000)",
    "offer_percent": 1.0
  },
  {
    "Id_Contract": 51,
    "Contract_Name": "MSE - Sec 19",
    "Offer_Id": "318075",
    "Owner": "MAIN STREET ENERGY CO LLC",
    "Group": null,
    "Source": null,
    "Offer_Status": null,
    "Contract_Desc": null,
    "Contract_Date": "/Date(1585621248753)/",
    "effective_date": "/Date(1575138600000)/",
    "status_desc": "Closed",
    "priority_desc": "High",
    "status": null,
    "TotalCount": 0,
    "nma25": 2.95313,
    "nma25ic": 2.953125,
    "grosscommssiontot": 55610.0,
    "closing_date": "/Date(1578940200000)/",
    "grantee": "OneMap II LLC(100.00000)",
    "offer_percent": 1.0
  },
  {
    "Id_Contract": 50,
    "Contract_Name": "MCM Permian, LLC",
    "Offer_Id": "344887",
    "Owner": null,
    "Group": null,
    "Source": null,
    "Offer_Status": null,
    "Contract_Desc": null,
    "Contract_Date": "/Date(1585553850840)/",
    "effective_date": "/Date(1564597800000)/",
    "status_desc": "Closed",
    "priority_desc": "High",
    "status": null,
    "TotalCount": 0,
    "nma25": 17.43825,
    "nma25ic": 17.438249907,
    "grosscommssiontot": 529220.98,
    "closing_date": "/Date(1580236200000)/",
    "grantee": "OneMap II LLC(100.00000)",
    "offer_percent": 1.0
  },
  {
    "Id_Contract": 49,
    "Contract_Name": "Culver, Jenifer",
    "Offer_Id": "318076",
    "Owner": "Culver, Jenifer",
    "Group": null,
    "Source": null,
    "Offer_Status": null,
    "Contract_Desc": null,
    "Contract_Date": "/Date(1585302166897)/",
    "effective_date": "/Date(1575138600000)/",
    "status_desc": "Closed",
    "priority_desc": "High",
    "status": null,
    "TotalCount": 0,
    "nma25": 3.15,
    "nma25ic": 3.150009,
    "grosscommssiontot": 115000.0,
    "closing_date": "/Date(1581359400000)/",
    "grantee": "OneMap II LLC(100.00000)",
    "offer_percent": 0.5
  },
  {
    "Id_Contract": 48,
    "Contract_Name": "Culver, Chance",
    "Offer_Id": "318077",
    "Owner": "Culver Chance",
    "Group": null,
    "Source": null,
    "Offer_Status": null,
    "Contract_Desc": null,
    "Contract_Date": "/Date(1585301686457)/",
    "effective_date": "/Date(1575138600000)/",
    "status_desc": "Closed",
    "priority_desc": "High",
    "status": null,
    "TotalCount": 0,
    "nma25": 3.15,
    "nma25ic": 3.150009,
    "grosscommssiontot": 115000.0,
    "closing_date": "/Date(1580236200000)/",
    "grantee": "OneMap II LLC(100.00000)",
    "offer_percent": 1.0
  },
  {
    "Id_Contract": 47,
    "Contract_Name": "Arete - Robert Adkison",
    "Offer_Id": "208985",
    "Owner": "ADKISON ROBERT G JR",
    "Group": null,
    "Source": null,
    "Offer_Status": null,
    "Contract_Desc": null,
    "Contract_Date": "/Date(1585289770353)/",
    "effective_date": "/Date(1575138600000)/",
    "status_desc": "Closed",
    "priority_desc": "High",
    "status": null,
    "TotalCount": 0,
    "nma25": 4.21874,
    "nma25ic": 4.2187512,
    "grosscommssiontot": 81253.18,
    "closing_date": "/Date(1581964200000)/",
    "grantee": "OneMap II LLC(100.00000)",
    "offer_percent": 1.0
  },
  {
    "Id_Contract": 46,
    "Contract_Name": "McClure, Shawn",
    "Offer_Id": "343996",
    "Owner": "SHAWN M MCCLURE",
    "Group": null,
    "Source": null,
    "Offer_Status": null,
    "Contract_Desc": null,
    "Contract_Date": "/Date(1585284019237)/",
    "effective_date": "/Date(1577817000000)/",
    "status_desc": "Closed",
    "priority_desc": "High",
    "status": null,
    "TotalCount": 0,
    "nma25": 7.5,
    "nma25ic": 7.5,
    "grosscommssiontot": 204000.0,
    "closing_date": "/Date(1583087400000)/",
    "grantee": "OneMap II LLC(100.00000)",
    "offer_percent": 1.0
  },
  {
    "Id_Contract": 45,
    "Contract_Name": "Levie, Elizabeth",
    "Offer_Id": "317683",
    "Owner": "LEVIE ELIZABETH ANN",
    "Group": null,
    "Source": null,
    "Offer_Status": null,
    "Contract_Desc": null,
    "Contract_Date": "/Date(1585214469883)/",
    "effective_date": "/Date(1572546600000)/",
    "status_desc": "Closed",
    "priority_desc": "High",
    "status": null,
    "TotalCount": 0,
    "nma25": 5.07392,
    "nma25ic": 5.07358152,
    "grosscommssiontot": 77000.0,
    "closing_date": "/Date(1583087400000)/",
    "grantee": "OneMap II LLC(100.00000)",
    "offer_percent": 1.0
  },
  {
    "Id_Contract": 44,
    "Contract_Name": "Lipkins, Edward",
    "Offer_Id": "344872",
    "Owner": "Lipkins, Edward",
    "Group": null,
    "Source": null,
    "Offer_Status": null,
    "Contract_Desc": null,
    "Contract_Date": "/Date(1585196775807)/",
    "effective_date": "/Date(1583001000000)/",
    "status_desc": "Closed",
    "priority_desc": "High",
    "status": null,
    "TotalCount": 0,
    "nma25": 19.125,
    "nma25ic": 19.125,
    "grosscommssiontot": 346409.0,
    "closing_date": "/Date(1583692200000)/",
    "grantee": "OneMap II LLC(100.00000)",
    "offer_percent": 0.5
  },
  {
    "Id_Contract": 43,
    "Contract_Name": "Contender Permian II, LP",
    "Offer_Id": "317999",
    "Owner": "CONTENDER ENERGY PARTNERS LP",
    "Group": null,
    "Source": null,
    "Offer_Status": null,
    "Contract_Desc": null,
    "Contract_Date": "/Date(1579058783637)/",
    "effective_date": "/Date(1561919400000)/",
    "status_desc": "Closed",
    "priority_desc": "High",
    "status": null,
    "TotalCount": 0,
    "nma25": 18.70584,
    "nma25ic": 18.7058461088,
    "grosscommssiontot": 448711.0,
    "closing_date": "/Date(1566412200000)/",
    "grantee": "OneMap II LLC(100.00000)",
    "offer_percent": 1.0
  },
  {
    "Id_Contract": 42,
    "Contract_Name": "Land, William Travis",
    "Offer_Id": "318046",
    "Owner": "LAND WILLIAM TRAVIS",
    "Group": null,
    "Source": null,
    "Offer_Status": null,
    "Contract_Desc": null,
    "Contract_Date": "/Date(1578476892823)/",
    "effective_date": "/Date(1569868200000)/",
    "status_desc": "Closed",
    "priority_desc": "High",
    "status": null,
    "TotalCount": 0,
    "nma25": 15.13788,
    "nma25ic": 15.1378919264,
    "grosscommssiontot": 251461.0,
    "closing_date": "/Date(1573065000000)/",
    "grantee": "OneMap II LLC(100.00000)",
    "offer_percent": 1.0
  },
  {
    "Id_Contract": 41,
    "Contract_Name": "F3 Criterion/Bellatorum - Ward",
    "Offer_Id": "289594",
    "Owner": "Bellatorum",
    "Group": null,
    "Source": null,
    "Offer_Status": null,
    "Contract_Desc": null,
    "Contract_Date": "/Date(1578390432617)/",
    "effective_date": "/Date(1556649000000)/",
    "status_desc": "Closed",
    "priority_desc": "High",
    "status": null,
    "TotalCount": 0,
    "nma25": 14.55312,
    "nma25ic": 14.5531215731473791,
    "grosscommssiontot": 297715.000829268,
    "closing_date": "/Date(1560882600000)/",
    "grantee": "OneMap II LLC(100.00000)",
    "offer_percent": 0.6315789
  },
  {
    "Id_Contract": 40,
    "Contract_Name": "F3 Criterion/Bellatorum - Upton",
    "Offer_Id": "289593",
    "Owner": "Bellatorum",
    "Group": null,
    "Source": null,
    "Offer_Status": null,
    "Contract_Desc": null,
    "Contract_Date": "/Date(1578369264620)/",
    "effective_date": "/Date(1556649000000)/",
    "status_desc": "Closed",
    "priority_desc": "High",
    "status": null,
    "TotalCount": 0,
    "nma25": 10.2,
    "nma25ic": 10.199999235,
    "grosscommssiontot": 242394.000767817,
    "closing_date": "/Date(1560882600000)/",
    "grantee": "OneMap II LLC(100.00000)",
    "offer_percent": 0.6315789
  },
  {
    "Id_Contract": 39,
    "Contract_Name": "F3 Criterion/Bellatorum - Glasscock",
    "Offer_Id": "289591",
    "Owner": "Bellatorum",
    "Group": null,
    "Source": null,
    "Offer_Status": null,
    "Contract_Desc": null,
    "Contract_Date": "/Date(1578368102057)/",
    "effective_date": "/Date(1556649000000)/",
    "status_desc": "Closed",
    "priority_desc": "High",
    "status": null,
    "TotalCount": 0,
    "nma25": 10.96421,
    "nma25ic": 10.9642095423158016,
    "grosscommssiontot": 100959.996638526,
    "closing_date": "/Date(1560882600000)/",
    "grantee": "OneMap II LLC(100.00000)",
    "offer_percent": 0.6315789
  },
  {
    "Id_Contract": 38,
    "Contract_Name": "Alan Ware/Bellatorum - Howard",
    "Offer_Id": "318000",
    "Owner": "Bellatorum",
    "Group": null,
    "Source": null,
    "Offer_Status": null,
    "Contract_Desc": null,
    "Contract_Date": "/Date(1578286773587)/",
    "effective_date": "/Date(1561919400000)/",
    "status_desc": "Closed",
    "priority_desc": "High",
    "status": null,
    "TotalCount": 0,
    "nma25": 10.4,
    "nma25ic": 10.4,
    "grosscommssiontot": 278722.0,
    "closing_date": "/Date(1564079400000)/",
    "grantee": "OneMap II LLC(100.00000)",
    "offer_percent": 0.5
  },
  {
    "Id_Contract": 37,
    "Contract_Name": "Wendel, Anna Nicole Land",
    "Offer_Id": "306151",
    "Owner": "LAND CARROLL DALE",
    "Group": null,
    "Source": null,
    "Offer_Status": null,
    "Contract_Desc": null,
    "Contract_Date": "/Date(1576808805070)/",
    "effective_date": "/Date(1569868200000)/",
    "status_desc": "Closed",
    "priority_desc": "High",
    "status": null,
    "TotalCount": 0,
    "nma25": 15.13788,
    "nma25ic": 15.1378919264,
    "grosscommssiontot": 251461.0,
    "closing_date": "/Date(1572373800000)/",
    "grantee": "OneMap II LLC(100.00000)",
    "offer_percent": 1.0
  },
  {
    "Id_Contract": 36,
    "Contract_Name": "Vatex Holdings LLC",
    "Offer_Id": "318045",
    "Owner": "VATEX HOLDINGS LLC",
    "Group": null,
    "Source": null,
    "Offer_Status": null,
    "Contract_Desc": null,
    "Contract_Date": "/Date(1576641788497)/",
    "effective_date": "/Date(1569868200000)/",
    "status_desc": "Closed",
    "priority_desc": "High",
    "status": null,
    "TotalCount": 0,
    "nma25": 28.37519,
    "nma25ic": 28.351999968,
    "grosscommssiontot": 975000.0,
    "closing_date": "/Date(1571077800000)/",
    "grantee": "OneMap II LLC(100.00000)",
    "offer_percent": 1.0
  },
  {
    "Id_Contract": 35,
    "Contract_Name": "Turley, Sarajane",
    "Offer_Id": "71934",
    "Owner": "WHITE SARAJANE",
    "Group": null,
    "Source": null,
    "Offer_Status": null,
    "Contract_Desc": null,
    "Contract_Date": "/Date(1576572326837)/",
    "effective_date": "/Date(1569868200000)/",
    "status_desc": "Closed",
    "priority_desc": "High",
    "status": null,
    "TotalCount": 0,
    "nma25": 1.07812,
    "nma25ic": 1.078124928,
    "grosscommssiontot": 25406.0,
    "closing_date": "/Date(1575829800000)/",
    "grantee": "OneMap II LLC(100.00000)",
    "offer_percent": 1.0
  },
  {
    "Id_Contract": 34,
    "Contract_Name": "Stone, Laurie Jane",
    "Offer_Id": "284769",
    "Owner": "STONE LAURIE JANE",
    "Group": null,
    "Source": null,
    "Offer_Status": null,
    "Contract_Desc": null,
    "Contract_Date": "/Date(1576571153993)/",
    "effective_date": "/Date(1556649000000)/",
    "status_desc": "Closed",
    "priority_desc": "High",
    "status": null,
    "TotalCount": 0,
    "nma25": 81.2625,
    "nma25ic": 81.2625,
    "grosscommssiontot": 1624761.9,
    "closing_date": "/Date(1562524200000)/",
    "grantee": "OneMap II LLC(100.00000)",
    "offer_percent": 1.0
  },
  {
    "Id_Contract": 33,
    "Contract_Name": "Short, John M",
    "Offer_Id": "202156",
    "Owner": "SHORT JOHN M",
    "Group": null,
    "Source": null,
    "Offer_Status": null,
    "Contract_Desc": null,
    "Contract_Date": "/Date(1576547688227)/",
    "effective_date": "/Date(1567276200000)/",
    "status_desc": "Closed",
    "priority_desc": "High",
    "status": null,
    "TotalCount": 0,
    "nma25": 5.32014,
    "nma25ic": 5.2637408744,
    "grosscommssiontot": 136857.34,
    "closing_date": "/Date(1572892200000)/",
    "grantee": "OneMap II LLC(100.00000)",
    "offer_percent": 1.0
  },
  {
    "Id_Contract": 32,
    "Contract_Name": "Short, James",
    "Offer_Id": "203059",
    "Owner": "SHORT JAMES A",
    "Group": null,
    "Source": null,
    "Offer_Status": null,
    "Contract_Desc": null,
    "Contract_Date": "/Date(1576546724080)/",
    "effective_date": "/Date(1567276200000)/",
    "status_desc": "Closed",
    "priority_desc": "High",
    "status": null,
    "TotalCount": 0,
    "nma25": 5.32014,
    "nma25ic": 5.263744004,
    "grosscommssiontot": 136857.34,
    "closing_date": "/Date(1572892200000)/",
    "grantee": "OneMap II LLC(100.00000)",
    "offer_percent": 1.0
  },
  {
    "Id_Contract": 31,
    "Contract_Name": "Neuhoff-Taylor Royalty Co",
    "Offer_Id": "272481",
    "Owner": "NEUHOFF TAYLOR ROYALTY CO",
    "Group": null,
    "Source": null,
    "Offer_Status": null,
    "Contract_Desc": null,
    "Contract_Date": "/Date(1576486955723)/",
    "effective_date": "/Date(1564597800000)/",
    "status_desc": "Closed",
    "priority_desc": "High",
    "status": null,
    "TotalCount": 0,
    "nma25": 48.42461,
    "nma25ic": 48.4246385122,
    "grosscommssiontot": 1798169.5,
    "closing_date": "/Date(1568313000000)/",
    "grantee": "OneMap II LLC(100.00000)",
    "offer_percent": 1.0
  },
  {
    "Id_Contract": 30,
    "Contract_Name": "Masarweh, Tony",
    "Offer_Id": "316508",
    "Owner": "MASARWEH TONY",
    "Group": null,
    "Source": null,
    "Offer_Status": null,
    "Contract_Desc": null,
    "Contract_Date": "/Date(1576465022093)/",
    "effective_date": "/Date(1567276200000)/",
    "status_desc": "Closed",
    "priority_desc": "High",
    "status": null,
    "TotalCount": 0,
    "nma25": 8.97083,
    "nma25ic": 8.970833334,
    "grosscommssiontot": 285000.0,
    "closing_date": "/Date(1569954600000)/",
    "grantee": "OneMap II LLC(100.00000)",
    "offer_percent": 1.0
  },
  {
    "Id_Contract": 29,
    "Contract_Name": "Lindley, Vickie Merrilyn / Arete",
    "Offer_Id": "306243",
    "Owner": "LINDLEY VICKI MERRILYN",
    "Group": null,
    "Source": null,
    "Offer_Status": null,
    "Contract_Desc": null,
    "Contract_Date": "/Date(1585814860013)/",
    "effective_date": "/Date(1564597800000)/",
    "status_desc": "Closed",
    "priority_desc": "High",
    "status": null,
    "TotalCount": 0,
    "nma25": 21.02365,
    "nma25ic": 20.7864349728,
    "grosscommssiontot": 360280.47,
    "closing_date": "/Date(1567103400000)/",
    "grantee": "OneMap II LLC(100.00000)",
    "offer_percent": 1.0
  },
  {
    "Id_Contract": 28,
    "Contract_Name": "Josey Oil Company",
    "Offer_Id": "249883",
    "Owner": "JOSEY OIL COMPANY",
    "Group": null,
    "Source": null,
    "Offer_Status": null,
    "Contract_Desc": null,
    "Contract_Date": "/Date(1576204871443)/",
    "effective_date": "/Date(1564597800000)/",
    "status_desc": "Closed",
    "priority_desc": "High",
    "status": null,
    "TotalCount": 0,
    "nma25": 112.0,
    "nma25ic": 111.999995184,
    "grosscommssiontot": 3070000.0,
    "closing_date": "/Date(1567708200000)/",
    "grantee": "OneMap II LLC(100.00000)",
    "offer_percent": 1.0
  },
  {
    "Id_Contract": 27,
    "Contract_Name": "Johnson, Thomas A",
    "Offer_Id": "261593",
    "Owner": "JOHNSON THOMAS A",
    "Group": null,
    "Source": null,
    "Offer_Status": null,
    "Contract_Desc": null,
    "Contract_Date": "/Date(1576203106903)/",
    "effective_date": "/Date(1559327400000)/",
    "status_desc": "Closed",
    "priority_desc": "High",
    "status": null,
    "TotalCount": 0,
    "nma25": 29.37596,
    "nma25ic": 29.3759497876,
    "grosscommssiontot": 1650000.0,
    "closing_date": "/Date(1562783400000)/",
    "grantee": "OneMap II LLC(100.00000)",
    "offer_percent": 1.0
  },
  {
    "Id_Contract": 26,
    "Contract_Name": "Grammer, Laurie Brooks",
    "Offer_Id": "191825",
    "Owner": "LAURIE B GRAMMER",
    "Group": null,
    "Source": null,
    "Offer_Status": null,
    "Contract_Desc": null,
    "Contract_Date": "/Date(1576201422630)/",
    "effective_date": "/Date(1567276200000)/",
    "status_desc": "Closed",
    "priority_desc": "High",
    "status": null,
    "TotalCount": 0,
    "nma25": 9.15245,
    "nma25ic": 9.15281072,
    "grosscommssiontot": 204000.0,
    "closing_date": "/Date(1570473000000)/",
    "grantee": "OneMap II LLC(100.00000)",
    "offer_percent": 1.0
  },
  {
    "Id_Contract": 25,
    "Contract_Name": "Gannaway, Mary Katherine",
    "Offer_Id": "214599",
    "Owner": "GANNAWAY JERRY M",
    "Group": null,
    "Source": null,
    "Offer_Status": null,
    "Contract_Desc": null,
    "Contract_Date": "/Date(1576141781447)/",
    "effective_date": "/Date(1567276200000)/",
    "status_desc": "Closed",
    "priority_desc": "High",
    "status": null,
    "TotalCount": 0,
    "nma25": 5.15873,
    "nma25ic": 5.1588069829,
    "grosscommssiontot": 125000.0,
    "closing_date": "/Date(1569781800000)/",
    "grantee": "OneMap II LLC(100.00000)",
    "offer_percent": 1.0
  },
  {
    "Id_Contract": 24,
    "Contract_Name": "Barnes, Susan A",
    "Offer_Id": "117885",
    "Owner": "BARNES SUSAN A",
    "Group": null,
    "Source": null,
    "Offer_Status": null,
    "Contract_Desc": null,
    "Contract_Date": "/Date(1575944652543)/",
    "effective_date": "/Date(1564597800000)/",
    "status_desc": "Closed",
    "priority_desc": "High",
    "status": null,
    "TotalCount": 0,
    "nma25": 9.875,
    "nma25ic": 9.8750016,
    "grosscommssiontot": 260000.0,
    "closing_date": "/Date(1570645800000)/",
    "grantee": "OneMap II LLC(100.00000)",
    "offer_percent": 1.0
  },
  {
    "Id_Contract": 23,
    "Contract_Name": "Stacey Uberstine Trust",
    "Offer_Id": "303820",
    "Owner": "UBERSTINE STACEY L BROWN TRUST",
    "Group": null,
    "Source": null,
    "Offer_Status": null,
    "Contract_Desc": null,
    "Contract_Date": "/Date(1573636577260)/",
    "effective_date": "/Date(1569868200000)/",
    "status_desc": "Closed",
    "priority_desc": "High",
    "status": null,
    "TotalCount": 0,
    "nma25": 16.15902,
    "nma25ic": 16.1587069659,
    "grosscommssiontot": 474999.9975,
    "closing_date": "/Date(1573583400000)/",
    "grantee": "OneMap II LLC(100.00000)",
    "offer_percent": 0.75
  },
  {
    "Id_Contract": 22,
    "Contract_Name": "Roberta Carson",
    "Offer_Id": "318032",
    "Owner": "Roberta Carson",
    "Group": null,
    "Source": null,
    "Offer_Status": null,
    "Contract_Desc": null,
    "Contract_Date": "/Date(1573623363657)/",
    "effective_date": "/Date(1567276200000)/",
    "status_desc": "Closed",
    "priority_desc": "High",
    "status": null,
    "TotalCount": 0,
    "nma25": 9.29784,
    "nma25ic": 9.29770325049624864,
    "grosscommssiontot": 275149.999151664,
    "closing_date": "/Date(1570645800000)/",
    "grantee": "OneMap II LLC(100.00000)",
    "offer_percent": 0.3333333
  },
  {
    "Id_Contract": 21,
    "Contract_Name": "Jason Jerry Menefee",
    "Offer_Id": "301702",
    "Owner": "MENEFEE JASON JERRY",
    "Group": null,
    "Source": null,
    "Offer_Status": null,
    "Contract_Desc": null,
    "Contract_Date": "/Date(1573618418283)/",
    "effective_date": "/Date(1569868200000)/",
    "status_desc": "Closed",
    "priority_desc": "High",
    "status": null,
    "TotalCount": 0,
    "nma25": 13.39542,
    "nma25ic": 13.39584532,
    "grosscommssiontot": 425000.0,
    "closing_date": "/Date(1572201000000)/",
    "grantee": "OneMap II LLC(100.00000)",
    "offer_percent": 1.0
  },
  {
    "Id_Contract": 20,
    "Contract_Name": "F3 Criterion - Davis/Bellatorum",
    "Offer_Id": "170674",
    "Owner": "MICHAEL GERARD DAVIS",
    "Group": null,
    "Source": null,
    "Offer_Status": null,
    "Contract_Desc": null,
    "Contract_Date": "/Date(1576729658187)/",
    "effective_date": "/Date(1556649000000)/",
    "status_desc": "Closed",
    "priority_desc": "High",
    "status": null,
    "TotalCount": 0,
    "nma25": 29.73854,
    "nma25ic": 29.89477431487432808,
    "grosscommssiontot": 508202.3623490775,
    "closing_date": "/Date(1561573800000)/",
    "grantee": "OneMap II LLC(100.00000)",
    "offer_percent": 0.77419355
  },
  {
    "Id_Contract": 19,
    "Contract_Name": "Patterson, LB",
    "Offer_Id": "278654",
    "Owner": "PATTERSON L B",
    "Group": null,
    "Source": null,
    "Offer_Status": null,
    "Contract_Desc": null,
    "Contract_Date": "/Date(1571132332297)/",
    "effective_date": "/Date(1556649000000)/",
    "status_desc": "Closed",
    "priority_desc": "High",
    "status": null,
    "TotalCount": 0,
    "nma25": 5.90625,
    "nma25ic": 5.90646,
    "grosscommssiontot": 118000.0,
    "closing_date": "/Date(1571077800000)/",
    "grantee": "OneMap II LLC(100.00000)",
    "offer_percent": 1.0
  },
  {
    "Id_Contract": 18,
    "Contract_Name": "Tarleton, Edward",
    "Offer_Id": "280834",
    "Owner": "Brawner_Reeves",
    "Group": null,
    "Source": null,
    "Offer_Status": null,
    "Contract_Desc": null,
    "Contract_Date": "/Date(1571130968500)/",
    "effective_date": "/Date(1561919400000)/",
    "status_desc": "Closed",
    "priority_desc": "High",
    "status": null,
    "TotalCount": 0,
    "nma25": 5.40313,
    "nma25ic": 5.40312177405,
    "grosscommssiontot": 152236.85,
    "closing_date": "/Date(1565116200000)/",
    "grantee": "OneMap II LLC(100.00000)",
    "offer_percent": 0.25
  },
  {
    "Id_Contract": 17,
    "Contract_Name": "Quail, Kevin",
    "Offer_Id": "216512",
    "Owner": "QUAIL KEVIN W TRUST",
    "Group": null,
    "Source": null,
    "Offer_Status": null,
    "Contract_Desc": null,
    "Contract_Date": "/Date(1569831050703)/",
    "effective_date": "/Date(1564597800000)/",
    "status_desc": "Closed",
    "priority_desc": "High",
    "status": null,
    "TotalCount": 0,
    "nma25": 2.22083,
    "nma25ic": 2.2208331502,
    "grosscommssiontot": 75000.0,
    "closing_date": "/Date(1570127400000)/",
    "grantee": "OneMap II LLC(100.00000)",
    "offer_percent": 1.0
  },
  {
    "Id_Contract": 16,
    "Contract_Name": "Parker, Jimmie R Jr",
    "Offer_Id": "288131",
    "Owner": "PARKER JIMMIE R",
    "Group": null,
    "Source": null,
    "Offer_Status": null,
    "Contract_Desc": null,
    "Contract_Date": "/Date(1568954718877)/",
    "effective_date": "/Date(1559327400000)/",
    "status_desc": "Closed",
    "priority_desc": "High",
    "status": null,
    "TotalCount": 0,
    "nma25": 5.02766,
    "nma25ic": 5.027591896,
    "grosscommssiontot": 195000.0,
    "closing_date": "/Date(1561660200000)/",
    "grantee": "OneMap II LLC(100.00000)",
    "offer_percent": 1.0
  },
  {
    "Id_Contract": 15,
    "Contract_Name": "Cook, Sammy",
    "Offer_Id": "238093",
    "Owner": "COOK SAMMY C",
    "Group": null,
    "Source": null,
    "Offer_Status": null,
    "Contract_Desc": null,
    "Contract_Date": "/Date(1568862975773)/",
    "effective_date": "/Date(1556649000000)/",
    "status_desc": "Closed",
    "priority_desc": "High",
    "status": null,
    "TotalCount": 0,
    "nma25": 52.10133,
    "nma25ic": 52.1013555241,
    "grosscommssiontot": 2000000.0,
    "closing_date": "/Date(1571077800000)/",
    "grantee": "OneMap II LLC(100.00000)",
    "offer_percent": 1.0
  },
  {
    "Id_Contract": 14,
    "Contract_Name": "Krueger, David",
    "Offer_Id": "300945",
    "Owner": "KRUEGER DAVID MD",
    "Group": null,
    "Source": null,
    "Offer_Status": null,
    "Contract_Desc": null,
    "Contract_Date": "/Date(1568860930570)/",
    "effective_date": "/Date(1561919400000)/",
    "status_desc": "Closed",
    "priority_desc": "High",
    "status": null,
    "TotalCount": 0,
    "nma25": 14.29313,
    "nma25ic": 14.293125,
    "grosscommssiontot": 700000.0,
    "closing_date": "/Date(1569349800000)/",
    "grantee": "OneMap II LLC(100.00000)",
    "offer_percent": 1.0
  },
  {
    "Id_Contract": 13,
    "Contract_Name": "Lewis, Hunter",
    "Offer_Id": "318029",
    "Owner": "Hunter Lane Lewis",
    "Group": null,
    "Source": null,
    "Offer_Status": null,
    "Contract_Desc": null,
    "Contract_Date": "/Date(1590047696593)/",
    "effective_date": "/Date(1567276200000)/",
    "status_desc": "Closed",
    "priority_desc": "High",
    "status": null,
    "TotalCount": 0,
    "nma25": 3.93969,
    "nma25ic": 4.8000009928,
    "grosscommssiontot": 92337.0,
    "closing_date": "/Date(1571077800000)/",
    "grantee": "OMJV1 Minerals Sub LP(100.00000)",
    "offer_percent": 1.0
  },
  {
    "Id_Contract": 12,
    "Contract_Name": "McLerran, Ian",
    "Offer_Id": "160730",
    "Owner": "MCLERRAN IAN JARED",
    "Group": null,
    "Source": null,
    "Offer_Status": null,
    "Contract_Desc": null,
    "Contract_Date": "/Date(1568858202570)/",
    "effective_date": "/Date(1556649000000)/",
    "status_desc": "Closed",
    "priority_desc": "High",
    "status": null,
    "TotalCount": 0,
    "nma25": 12.44433,
    "nma25ic": 12.4426266409,
    "grosscommssiontot": 315603.0,
    "closing_date": "/Date(1561660200000)/",
    "grantee": "OneMap II LLC(100.00000)",
    "offer_percent": 1.0
  },
  {
    "Id_Contract": 11,
    "Contract_Name": "Butler, Charles",
    "Offer_Id": "168762",
    "Owner": "BUTLER CHARLES",
    "Group": null,
    "Source": null,
    "Offer_Status": null,
    "Contract_Desc": null,
    "Contract_Date": "/Date(1568794714583)/",
    "effective_date": "/Date(1564597800000)/",
    "status_desc": "Closed",
    "priority_desc": "High",
    "status": null,
    "TotalCount": 0,
    "nma25": 39.48142,
    "nma25ic": 42.3085238235,
    "grosscommssiontot": 862500.0,
    "closing_date": "/Date(1565634600000)/",
    "grantee": "OneMap II LLC(100.00000)",
    "offer_percent": 0.5
  },
  {
    "Id_Contract": 10,
    "Contract_Name": "Sledge, David",
    "Offer_Id": "290928",
    "Owner": "DAVID W SLEDGE",
    "Group": null,
    "Source": null,
    "Offer_Status": null,
    "Contract_Desc": null,
    "Contract_Date": "/Date(1568779580940)/",
    "effective_date": "/Date(1564597800000)/",
    "status_desc": "Closed",
    "priority_desc": "High",
    "status": null,
    "TotalCount": 0,
    "nma25": 24.41597,
    "nma25ic": 24.628578864,
    "grosscommssiontot": 575270.0,
    "closing_date": "/Date(1567017000000)/",
    "grantee": "OneMap II LLC(100.00000)",
    "offer_percent": 1.0
  },
  {
    "Id_Contract": 8,
    "Contract_Name": "Marcel, Paul",
    "Offer_Id": "318005",
    "Owner": "MARCEL PAUL WILLIAM",
    "Group": null,
    "Source": null,
    "Offer_Status": null,
    "Contract_Desc": null,
    "Contract_Date": "/Date(1568701655440)/",
    "effective_date": "/Date(1564597800000)/",
    "status_desc": "Closed",
    "priority_desc": "High",
    "status": null,
    "TotalCount": 0,
    "nma25": 5.06,
    "nma25ic": 5.1189976974,
    "grosscommssiontot": 220000.0,
    "closing_date": "/Date(1568053800000)/",
    "grantee": "OneMap II LLC(100.00000)",
    "offer_percent": 1.0
  },
  {
    "Id_Contract": 7,
    "Contract_Name": "Hydrocarbon Holdings LTD",
    "Offer_Id": "305839",
    "Owner": "HYDROCARBON HOLDING LTD",
    "Group": null,
    "Source": null,
    "Offer_Status": null,
    "Contract_Desc": null,
    "Contract_Date": "/Date(1568688374590)/",
    "effective_date": "/Date(1567276200000)/",
    "status_desc": "Closed",
    "priority_desc": "High",
    "status": null,
    "TotalCount": 0,
    "nma25": 12.66667,
    "nma25ic": 12.6667264,
    "grosscommssiontot": 300000.0,
    "closing_date": "/Date(1568053800000)/",
    "grantee": "OneMap II LLC(100.00000)",
    "offer_percent": 1.0
  },
  {
    "Id_Contract": 6,
    "Contract_Name": "Forgeron, Theodore",
    "Offer_Id": "130125",
    "Owner": "THEODORE W JR FORGERON",
    "Group": null,
    "Source": null,
    "Offer_Status": null,
    "Contract_Desc": null,
    "Contract_Date": "/Date(1568021556437)/",
    "effective_date": "/Date(1556649000000)/",
    "status_desc": "Closed",
    "priority_desc": "High",
    "status": null,
    "TotalCount": 0,
    "nma25": 4.73166,
    "nma25ic": 4.731628512,
    "grosscommssiontot": 118673.0,
    "closing_date": "/Date(1561660200000)/",
    "grantee": "OneMap II LLC(100.00000)",
    "offer_percent": 1.0
  },
  {
    "Id_Contract": 5,
    "Contract_Name": "Lee, Cameron Cody",
    "Offer_Id": "214983",
    "Owner": "LEE CAMERON CODY",
    "Group": null,
    "Source": null,
    "Offer_Status": null,
    "Contract_Desc": null,
    "Contract_Date": "/Date(1568003741590)/",
    "effective_date": "/Date(1559327400000)/",
    "status_desc": "Closed",
    "priority_desc": "High",
    "status": null,
    "TotalCount": 0,
    "nma25": 2.8,
    "nma25ic": 2.8,
    "grosscommssiontot": 82656.0,
    "closing_date": "/Date(1561660200000)/",
    "grantee": "OneMap II LLC(100.00000)",
    "offer_percent": 1.0
  },
  {
    "Id_Contract": 4,
    "Contract_Name": "Bush, Warren, et al - Cowboy",
    "Offer_Id": "317202",
    "Owner": "BUSH WARREN V",
    "Group": null,
    "Source": null,
    "Offer_Status": null,
    "Contract_Desc": null,
    "Contract_Date": "/Date(1567655766113)/",
    "effective_date": "/Date(1564597800000)/",
    "status_desc": "Closed",
    "priority_desc": "High",
    "status": null,
    "TotalCount": 0,
    "nma25": 43.5,
    "nma25ic": 43.499999958,
    "grosscommssiontot": 1260000.0,
    "closing_date": "/Date(1566757800000)/",
    "grantee": "OneMap II LLC(100.00000)",
    "offer_percent": 1.0
  },
  {
    "Id_Contract": 3,
    "Contract_Name": "DEF Oil Partners",
    "Offer_Id": "275460",
    "Owner": "DEF OIL PARTNERS",
    "Group": null,
    "Source": null,
    "Offer_Status": null,
    "Contract_Desc": null,
    "Contract_Date": "/Date(1567587409250)/",
    "effective_date": "/Date(1559327400000)/",
    "status_desc": "Dead Deal",
    "priority_desc": "High",
    "status": null,
    "TotalCount": 0,
    "nma25": 6.0,
    "nma25ic": 6.000005,
    "grosscommssiontot": 100236.0,
    "closing_date": "/Date(1562783400000)/",
    "grantee": "OneMap II LLC(100.00000)",
    "offer_percent": 0.5
  }
]
